dicomraw/__init__.py
dicomraw/archive.py
dicomraw/wrap.py
dicomraw-0.4.0.3.data/scripts/dicomunwrap
dicomraw-0.4.0.3.dist-info/METADATA
dicomraw-0.4.0.3.dist-info/RECORD
dicomraw-0.4.0.3.dist-info/WHEEL
dicomraw-0.4.0.3.dist-info/top_level.txt
